django_api_gen/__init__.py
django_api_gen/manager.py
django_api_gen/util.py
django_api_gen/web.py
django_api_gen/__pycache__/__init__.cpython-39.pyc
django_api_gen/__pycache__/manager.cpython-39.pyc
django_api_gen/__pycache__/util.cpython-39.pyc
django_api_gen/__pycache__/web.cpython-39.pyc
django_api_gen/admin/__init__.py
django_api_gen/admin/admin_structure
django_api_gen/admin/base_admin
django_api_gen/admin/base_imports
django_api_gen/admin/library_imports
django_api_gen/admin/__pycache__/__init__.cpython-39.pyc
django_api_gen/api/__init__.py
django_api_gen/api/serializers.py
django_api_gen/api/urls.py
django_api_gen/api/views.py
django_api_gen/api/__pycache__/__init__.cpython-39.pyc
django_api_gen/apps/__init__.py
django_api_gen/apps/apps_structure
django_api_gen/apps/__pycache__/__init__.cpython-39.pyc
django_api_gen/management/__init__.py
django_api_gen/management/__pycache__/__init__.cpython-39.pyc
django_api_gen/management/commands/__init__.py
django_api_gen/management/commands/generate-api.py
django_api_gen/management/commands/generate-web.py
django_api_gen/management/commands/__pycache__/__init__.cpython-39.pyc
django_api_gen/management/commands/__pycache__/generate-api.cpython-39.pyc
django_api_gen/management/commands/__pycache__/generate-web.cpython-39.pyc
django_api_gen/serializers/__init__.py
django_api_gen/serializers/base_imports
django_api_gen/serializers/base_serializer
django_api_gen/serializers/foreign_serializers
django_api_gen/serializers/library_imports
django_api_gen/serializers/serializers_structure
django_api_gen/serializers/__pycache__/__init__.cpython-39.pyc
django_api_gen/urls/__init__.py
django_api_gen/urls/base_imports
django_api_gen/urls/base_urls_path
django_api_gen/urls/library_imports
django_api_gen/urls/urls_structure
django_api_gen/urls/__pycache__/__init__.cpython-39.pyc
django_api_gen/views/__init__.py
django_api_gen/views/base_imports
django_api_gen/views/base_views
django_api_gen/views/library_imports
django_next_gen-0.1.1.dist-info/licenses/LICENSE.md
django_next_gen-0.1.1.dist-info/METADATA
django_next_gen-0.1.1.dist-info/WHEEL
django_next_gen-0.1.1.dist-info/top_level.txt
django_next_gen-0.1.1.dist-info/RECORD
