Metadata-Version: 2.4
Name: django-next-gen
Version: 0.1.1
Summary: A Django Next generator
Home-page: https://app-generator.dev/docs/developer-tools/api-generator.html
Author: AppSeed.us
Author-email: Yohannes Abera <yohannesabera1236@gmail.com>
License: MIT
Requires-Python: >=3.7
License-File: LICENSE.md
Dynamic: author
Dynamic: home-page
Dynamic: license-file
